{
  "last_scan_ist": "27-May-2026 16:36 IST",
  "last_india_scan_ist": "27-May-2026 00:57 IST",
  "last_us_scan_ist": "27-May-2026 16:36 IST",
  "usd_inr": 95.5,
  "india": {
    "buys": [
      {
        "symbol": "BHEL",
        "name": "Bharat Heavy Electricals Ltd.",
        "sector": "Capital Goods",
        "current_price": 419.4,
        "high52w": 420.95,
        "low52w": 208.01,
        "ath_target": 378.86,
        "entry_mode": 90,
        "pct_from_high": -0.37,
        "suggested_floor": 335.52,
        "suggested_qty": 238,
        "suggested_amount": 99817.2,
        "currency": "\u20b9"
      },
      {
        "symbol": "APOLLOHOSP",
        "name": "Apollo Hospitals Enterprise Ltd.",
        "sector": "Healthcare",
        "current_price": 8404.0,
        "high52w": 8443.0,
        "low52w": 6793.5,
        "ath_target": 7598.7,
        "entry_mode": 90,
        "pct_from_high": -0.46,
        "suggested_floor": 6723.2,
        "suggested_qty": 11,
        "suggested_amount": 92444.0,
        "currency": "\u20b9"
      },
      {
        "symbol": "SAILIFE",
        "name": "Sai Life Sciences Ltd.",
        "sector": "Healthcare",
        "current_price": 1175.9,
        "high52w": 1184.8,
        "low52w": 716.65,
        "ath_target": 1066.32,
        "entry_mode": 90,
        "pct_from_high": -0.75,
        "suggested_floor": 940.72,
        "suggested_qty": 85,
        "suggested_amount": 99951.5,
        "currency": "\u20b9"
      },
      {
        "symbol": "GRASIM",
        "name": "Grasim Industries Ltd.",
        "sector": "Construction Materials",
        "current_price": 3171.6,
        "high52w": 3196.2,
        "low52w": 2524.1,
        "ath_target": 2876.58,
        "entry_mode": 90,
        "pct_from_high": -0.77,
        "suggested_floor": 2537.28,
        "suggested_qty": 31,
        "suggested_amount": 98319.6,
        "currency": "\u20b9"
      },
      {
        "symbol": "NAVINFLUOR",
        "name": "Navin Fluorine International Ltd.",
        "sector": "Chemicals",
        "current_price": 7445.5,
        "high52w": 7525.0,
        "low52w": 4249.9,
        "ath_target": 6772.5,
        "entry_mode": 90,
        "pct_from_high": -1.06,
        "suggested_floor": 5956.4,
        "suggested_qty": 13,
        "suggested_amount": 96791.5,
        "currency": "\u20b9"
      },
      {
        "symbol": "ACUTAAS",
        "name": "Acutaas Chemicals Ltd.",
        "sector": "Healthcare",
        "current_price": 3034.8,
        "high52w": 3069.0,
        "low52w": 1086.4,
        "ath_target": 2762.1,
        "entry_mode": 90,
        "pct_from_high": -1.11,
        "suggested_floor": 2427.84,
        "suggested_qty": 32,
        "suggested_amount": 97113.6,
        "currency": "\u20b9"
      },
      {
        "symbol": "IDEA",
        "name": "Vodafone Idea Ltd.",
        "sector": "Telecommunication",
        "current_price": 14.04,
        "high52w": 14.2,
        "low52w": 6.15,
        "ath_target": 12.78,
        "entry_mode": 90,
        "pct_from_high": -1.13,
        "suggested_floor": 11.23,
        "suggested_qty": 7122,
        "suggested_amount": 99992.88,
        "currency": "\u20b9"
      },
      {
        "symbol": "ADANIPORTS",
        "name": "Adani Ports and Special Economic Zone Ltd.",
        "sector": "Services",
        "current_price": 1802.9,
        "high52w": 1823.9,
        "low52w": 1300.3,
        "ath_target": 1641.51,
        "entry_mode": 90,
        "pct_from_high": -1.15,
        "suggested_floor": 1442.32,
        "suggested_qty": 55,
        "suggested_amount": 99159.5,
        "currency": "\u20b9"
      },
      {
        "symbol": "KEI",
        "name": "KEI Industries Ltd.",
        "sector": "Capital Goods",
        "current_price": 5281.5,
        "high52w": 5345.0,
        "low52w": 3496.4,
        "ath_target": 4810.5,
        "entry_mode": 90,
        "pct_from_high": -1.19,
        "suggested_floor": 4225.2,
        "suggested_qty": 18,
        "suggested_amount": 95067.0,
        "currency": "\u20b9"
      },
      {
        "symbol": "ANGELONE",
        "name": "Angel One Ltd.",
        "sector": "Financial Services",
        "current_price": 346.45,
        "high52w": 351.0,
        "low52w": 212.49,
        "ath_target": 315.9,
        "entry_mode": 90,
        "pct_from_high": -1.3,
        "suggested_floor": 277.16,
        "suggested_qty": 288,
        "suggested_amount": 99777.6,
        "currency": "\u20b9"
      },
      {
        "symbol": "LAURUSLABS",
        "name": "Laurus Labs Ltd.",
        "sector": "Healthcare",
        "current_price": 1356.3,
        "high52w": 1376.9,
        "low52w": 595.05,
        "ath_target": 1239.21,
        "entry_mode": 90,
        "pct_from_high": -1.5,
        "suggested_floor": 1085.04,
        "suggested_qty": 73,
        "suggested_amount": 99009.9,
        "currency": "\u20b9"
      },
      {
        "symbol": "CUMMINSIND",
        "name": "Cummins India Ltd.",
        "sector": "Capital Goods",
        "current_price": 5382.0,
        "high52w": 5470.5,
        "low52w": 2944.6,
        "ath_target": 4923.45,
        "entry_mode": 90,
        "pct_from_high": -1.62,
        "suggested_floor": 4305.6,
        "suggested_qty": 18,
        "suggested_amount": 96876.0,
        "currency": "\u20b9"
      },
      {
        "symbol": "SOLARINDS",
        "name": "Solar Industries India Ltd.",
        "sector": "Chemicals",
        "current_price": 18377.0,
        "high52w": 18699.0,
        "low52w": 11772.0,
        "ath_target": 16829.1,
        "entry_mode": 90,
        "pct_from_high": -1.72,
        "suggested_floor": 14701.6,
        "suggested_qty": 5,
        "suggested_amount": 91885.0,
        "currency": "\u20b9"
      },
      {
        "symbol": "ADANIENSOL",
        "name": "Adani Energy Solutions Ltd.",
        "sector": "Power",
        "current_price": 1463.3,
        "high52w": 1489.0,
        "low52w": 755.95,
        "ath_target": 1340.1,
        "entry_mode": 90,
        "pct_from_high": -1.73,
        "suggested_floor": 1170.64,
        "suggested_qty": 68,
        "suggested_amount": 99504.4,
        "currency": "\u20b9"
      },
      {
        "symbol": "HINDALCO",
        "name": "Hindalco Industries Ltd.",
        "sector": "Metals & Mining",
        "current_price": 1099.6,
        "high52w": 1119.8,
        "low52w": 631.1,
        "ath_target": 1007.82,
        "entry_mode": 90,
        "pct_from_high": -1.8,
        "suggested_floor": 879.68,
        "suggested_qty": 90,
        "suggested_amount": 98964.0,
        "currency": "\u20b9"
      },
      {
        "symbol": "JSWSTEEL",
        "name": "JSW Steel Ltd.",
        "sector": "Metals & Mining",
        "current_price": 1289.4,
        "high52w": 1314.0,
        "low52w": 968.55,
        "ath_target": 1182.6,
        "entry_mode": 90,
        "pct_from_high": -1.87,
        "suggested_floor": 1031.52,
        "suggested_qty": 77,
        "suggested_amount": 99283.8,
        "currency": "\u20b9"
      },
      {
        "symbol": "RBLBANK",
        "name": "RBL Bank Ltd.",
        "sector": "Financial Services",
        "current_price": 343.35,
        "high52w": 349.9,
        "low52w": 204.62,
        "ath_target": 314.91,
        "entry_mode": 90,
        "pct_from_high": -1.87,
        "suggested_floor": 274.68,
        "suggested_qty": 291,
        "suggested_amount": 99914.85,
        "currency": "\u20b9"
      },
      {
        "symbol": "ZYDUSLIFE",
        "name": "Zydus Lifesciences Ltd.",
        "sector": "Healthcare",
        "current_price": 1072.95,
        "high52w": 1093.65,
        "low52w": 860.6,
        "ath_target": 984.29,
        "entry_mode": 90,
        "pct_from_high": -1.89,
        "suggested_floor": 858.36,
        "suggested_qty": 93,
        "suggested_amount": 99784.35,
        "currency": "\u20b9"
      },
      {
        "symbol": "NAM-INDIA",
        "name": "Nippon Life India Asset Management Ltd.",
        "sector": "Financial Services",
        "current_price": 1100.1,
        "high52w": 1125.0,
        "low52w": 724.45,
        "ath_target": 1012.5,
        "entry_mode": 90,
        "pct_from_high": -2.21,
        "suggested_floor": 880.08,
        "suggested_qty": 90,
        "suggested_amount": 99009.0,
        "currency": "\u20b9"
      },
      {
        "symbol": "MOTHERSON",
        "name": "Samvardhana Motherson International Ltd.",
        "sector": "Automobile and Auto Components",
        "current_price": 135.91,
        "high52w": 139.01,
        "low52w": 90.27,
        "ath_target": 125.11,
        "entry_mode": 90,
        "pct_from_high": -2.23,
        "suggested_floor": 108.73,
        "suggested_qty": 735,
        "suggested_amount": 99893.85,
        "currency": "\u20b9"
      }
    ],
    "sells": [],
    "floors": [],
    "portfolio": [],
    "stats": {
      "scanned": 500,
      "universe": 504,
      "buy_signals": 20,
      "sell_signals": 0,
      "floor_updates": 0,
      "slots_free": 20,
      "scan_seconds": 21.9
    },
    "scan_time_ist": "27-May-2026 00:57 IST"
  },
  "us": {
    "buys": [],
    "sells": [],
    "floors": [],
    "portfolio": [],
    "stats": {
      "scanned": 258,
      "universe": 265,
      "buy_signals": 0,
      "sell_signals": 0,
      "floor_updates": 0,
      "slots_free": 20,
      "scan_seconds": 17.3
    },
    "scan_time_ist": "27-May-2026 16:36 IST"
  }
}