{
  "last_scan_ist": "13-Jul-2026 18:32 IST",
  "last_india_scan_ist": "13-Jul-2026 18:32 IST",
  "last_us_scan_ist": "11-Jul-2026 04:02 IST",
  "usd_inr": 95.5,
  "india": {
    "buys": [
      {
        "symbol": "RBLBANK",
        "name": "RBL Bank Ltd.",
        "sector": "Financial Services",
        "current_price": 380.6,
        "high52w": 382.1,
        "low52w": 250.85,
        "ath_target": 343.89,
        "entry_mode": 90,
        "pct_from_high": -0.39,
        "suggested_floor": 304.48,
        "suggested_qty": 262,
        "suggested_amount": 99717.2,
        "currency": "\u20b9"
      },
      {
        "symbol": "DIVISLAB",
        "name": "Divi's Laboratories Ltd.",
        "sector": "Healthcare",
        "current_price": 6938.5,
        "high52w": 6968.0,
        "low52w": 5689.5,
        "ath_target": 6271.2,
        "entry_mode": 90,
        "pct_from_high": -0.42,
        "suggested_floor": 5550.8,
        "suggested_qty": 14,
        "suggested_amount": 97139.0,
        "currency": "\u20b9"
      },
      {
        "symbol": "LAURUSLABS",
        "name": "Laurus Labs Ltd.",
        "sector": "Healthcare",
        "current_price": 1558.6,
        "high52w": 1565.4,
        "low52w": 821.5,
        "ath_target": 1408.86,
        "entry_mode": 90,
        "pct_from_high": -0.43,
        "suggested_floor": 1246.88,
        "suggested_qty": 64,
        "suggested_amount": 99750.4,
        "currency": "\u20b9"
      },
      {
        "symbol": "PHOENIXLTD",
        "name": "Phoenix Mills Ltd.",
        "sector": "Realty",
        "current_price": 2154.0,
        "high52w": 2163.4,
        "low52w": 1417.3,
        "ath_target": 1947.06,
        "entry_mode": 90,
        "pct_from_high": -0.43,
        "suggested_floor": 1723.2,
        "suggested_qty": 46,
        "suggested_amount": 99084.0,
        "currency": "\u20b9"
      },
      {
        "symbol": "TORNTPHARM",
        "name": "Torrent Pharmaceuticals Ltd.",
        "sector": "Healthcare",
        "current_price": 4951.1,
        "high52w": 4973.0,
        "low52w": 3404.9,
        "ath_target": 4475.7,
        "entry_mode": 90,
        "pct_from_high": -0.44,
        "suggested_floor": 3960.88,
        "suggested_qty": 20,
        "suggested_amount": 99022.0,
        "currency": "\u20b9"
      },
      {
        "symbol": "WELSPUNLIV",
        "name": "Welspun Living Ltd.",
        "sector": "Textiles",
        "current_price": 174.14,
        "high52w": 174.97,
        "low52w": 108.32,
        "ath_target": 157.47,
        "entry_mode": 90,
        "pct_from_high": -0.47,
        "suggested_floor": 139.31,
        "suggested_qty": 574,
        "suggested_amount": 99956.36,
        "currency": "\u20b9"
      },
      {
        "symbol": "JBCHEPHARM",
        "name": "J.B. Chemicals & Pharmaceuticals Ltd.",
        "sector": "Healthcare",
        "current_price": 2460.0,
        "high52w": 2474.0,
        "low52w": 1637.9,
        "ath_target": 2226.6,
        "entry_mode": 90,
        "pct_from_high": -0.57,
        "suggested_floor": 1968.0,
        "suggested_qty": 40,
        "suggested_amount": 98400.0,
        "currency": "\u20b9"
      },
      {
        "symbol": "PAYTM",
        "name": "One 97 Communications Ltd.",
        "sector": "Financial Services",
        "current_price": 1386.5,
        "high52w": 1397.4,
        "low52w": 959.0,
        "ath_target": 1257.66,
        "entry_mode": 90,
        "pct_from_high": -0.78,
        "suggested_floor": 1109.2,
        "suggested_qty": 72,
        "suggested_amount": 99828.0,
        "currency": "\u20b9"
      },
      {
        "symbol": "ABCAPITAL",
        "name": "Aditya Birla Capital Ltd.",
        "sector": "Financial Services",
        "current_price": 407.45,
        "high52w": 410.7,
        "low52w": 248.8,
        "ath_target": 369.63,
        "entry_mode": 90,
        "pct_from_high": -0.79,
        "suggested_floor": 325.96,
        "suggested_qty": 245,
        "suggested_amount": 99825.25,
        "currency": "\u20b9"
      },
      {
        "symbol": "GMRAIRPORT",
        "name": "GMR Airports Ltd.",
        "sector": "Services",
        "current_price": 114.68,
        "high52w": 115.64,
        "low52w": 84.75,
        "ath_target": 104.08,
        "entry_mode": 90,
        "pct_from_high": -0.83,
        "suggested_floor": 91.74,
        "suggested_qty": 871,
        "suggested_amount": 99886.28,
        "currency": "\u20b9"
      },
      {
        "symbol": "IPCALAB",
        "name": "Ipca Laboratories Ltd.",
        "sector": "Healthcare",
        "current_price": 1823.3,
        "high52w": 1838.5,
        "low52w": 1268.7,
        "ath_target": 1654.65,
        "entry_mode": 90,
        "pct_from_high": -0.83,
        "suggested_floor": 1458.64,
        "suggested_qty": 54,
        "suggested_amount": 98458.2,
        "currency": "\u20b9"
      },
      {
        "symbol": "SHYAMMETL",
        "name": "Shyam Metalics and Energy Ltd.",
        "sector": "Capital Goods",
        "current_price": 1029.35,
        "high52w": 1038.0,
        "low52w": 761.45,
        "ath_target": 934.2,
        "entry_mode": 90,
        "pct_from_high": -0.83,
        "suggested_floor": 823.48,
        "suggested_qty": 97,
        "suggested_amount": 99846.95,
        "currency": "\u20b9"
      },
      {
        "symbol": "CEMPRO",
        "name": "Cemindia Projects Ltd.",
        "sector": "Construction",
        "current_price": 1583.7,
        "high52w": 1597.4,
        "low52w": 509.7,
        "ath_target": 1437.66,
        "entry_mode": 90,
        "pct_from_high": -0.86,
        "suggested_floor": 1266.96,
        "suggested_qty": 63,
        "suggested_amount": 99773.1,
        "currency": "\u20b9"
      },
      {
        "symbol": "PNBHOUSING",
        "name": "PNB Housing Finance Ltd.",
        "sector": "Financial Services",
        "current_price": 1122.3,
        "high52w": 1132.7,
        "low52w": 750.75,
        "ath_target": 1019.43,
        "entry_mode": 90,
        "pct_from_high": -0.92,
        "suggested_floor": 897.84,
        "suggested_qty": 89,
        "suggested_amount": 99884.7,
        "currency": "\u20b9"
      },
      {
        "symbol": "CCL",
        "name": "CCL Products (I) Ltd.",
        "sector": "Fast Moving Consumer Goods",
        "current_price": 1229.7,
        "high52w": 1242.2,
        "low52w": 829.25,
        "ath_target": 1117.98,
        "entry_mode": 90,
        "pct_from_high": -1.01,
        "suggested_floor": 983.76,
        "suggested_qty": 81,
        "suggested_amount": 99605.7,
        "currency": "\u20b9"
      },
      {
        "symbol": "GRANULES",
        "name": "Granules India Ltd.",
        "sector": "Healthcare",
        "current_price": 897.65,
        "high52w": 907.8,
        "low52w": 439.35,
        "ath_target": 817.02,
        "entry_mode": 90,
        "pct_from_high": -1.12,
        "suggested_floor": 718.12,
        "suggested_qty": 111,
        "suggested_amount": 99639.15,
        "currency": "\u20b9"
      },
      {
        "symbol": "NYKAA",
        "name": "FSN E-Commerce Ventures Ltd.",
        "sector": "Consumer Services",
        "current_price": 328.4,
        "high52w": 332.15,
        "low52w": 202.13,
        "ath_target": 298.94,
        "entry_mode": 90,
        "pct_from_high": -1.13,
        "suggested_floor": 262.72,
        "suggested_qty": 304,
        "suggested_amount": 99833.6,
        "currency": "\u20b9"
      },
      {
        "symbol": "WELCORP",
        "name": "Welspun Corp Ltd.",
        "sector": "Capital Goods",
        "current_price": 1619.9,
        "high52w": 1638.8,
        "low52w": 721.85,
        "ath_target": 1474.92,
        "entry_mode": 90,
        "pct_from_high": -1.15,
        "suggested_floor": 1295.92,
        "suggested_qty": 61,
        "suggested_amount": 98813.9,
        "currency": "\u20b9"
      },
      {
        "symbol": "FEDERALBNK",
        "name": "Federal Bank Ltd.",
        "sector": "Financial Services",
        "current_price": 332.5,
        "high52w": 336.5,
        "low52w": 189.9,
        "ath_target": 302.85,
        "entry_mode": 90,
        "pct_from_high": -1.19,
        "suggested_floor": 266.0,
        "suggested_qty": 300,
        "suggested_amount": 99750.0,
        "currency": "\u20b9"
      },
      {
        "symbol": "SAILIFE",
        "name": "Sai Life Sciences Ltd.",
        "sector": "Healthcare",
        "current_price": 1272.1,
        "high52w": 1288.0,
        "low52w": 788.0,
        "ath_target": 1159.2,
        "entry_mode": 90,
        "pct_from_high": -1.23,
        "suggested_floor": 1017.68,
        "suggested_qty": 78,
        "suggested_amount": 99223.8,
        "currency": "\u20b9"
      }
    ],
    "sells": [],
    "floors": [],
    "portfolio": [],
    "stats": {
      "scanned": 500,
      "universe": 500,
      "buy_signals": 20,
      "sell_signals": 0,
      "floor_updates": 0,
      "slots_free": 20,
      "scan_seconds": 36.7
    },
    "scan_time_ist": "13-Jul-2026 18:32 IST"
  },
  "us": {
    "buys": [],
    "sells": [],
    "floors": [],
    "portfolio": [],
    "stats": {
      "scanned": 257,
      "universe": 265,
      "buy_signals": 0,
      "sell_signals": 0,
      "floor_updates": 0,
      "slots_free": 20,
      "scan_seconds": 13.2
    },
    "scan_time_ist": "11-Jul-2026 04:02 IST"
  }
}